bsm/__init__.py
bsm/bsm.py
bsm/exceptions.py
bsm/functions.py
buzzsprout_manager-0.0.3.dist-info/LICENSE
buzzsprout_manager-0.0.3.dist-info/METADATA
buzzsprout_manager-0.0.3.dist-info/WHEEL
buzzsprout_manager-0.0.3.dist-info/top_level.txt
buzzsprout_manager-0.0.3.dist-info/RECORD
