Metadata-Version: 2.1
Name: buzzsprout-manager
Version: 0.0.3
Summary: A python wrapper for the Buzzsprout API
Home-page: https://github.com/deancolten/buzzsprout-manager
Author: Colten Dean
Author-email: coltenrdean@gmail.com
License: UNKNOWN
Platform: UNKNOWN
Classifier: Programming Language :: Python :: 3
Classifier: Operating System :: OS Independent
Requires-Dist: requests-toolbelt
